limonata/__init__.py
limonata/_lib.py
limonata/_modidx.py
limonata-0.0.2.dist-info/LICENSE
limonata-0.0.2.dist-info/METADATA
limonata-0.0.2.dist-info/WHEEL
limonata-0.0.2.dist-info/entry_points.txt
limonata-0.0.2.dist-info/top_level.txt
limonata-0.0.2.dist-info/RECORD
