Metadata-Version: 2.1
Name: limonata
Version: 0.0.2
Summary: A marvellous resource for giving your plots the perfect touch of color they deserve.
Home-page: https://github.com/sarraahr/limonata
Author: Sarah Sobotta, Can Demircan
Author-email: sarah.sobotta@gmx.de
License: Apache Software License 2.0
Keywords: color palettes plotting matplotlib aesthetic
Classifier: Development Status :: 4 - Beta
Classifier: Intended Audience :: Developers
Classifier: Natural Language :: English
Classifier: Programming Language :: Python :: 3.6
Classifier: Programming Language :: Python :: 3.7
Classifier: Programming Language :: Python :: 3.8
Classifier: Programming Language :: Python :: 3.9
Classifier: Programming Language :: Python :: 3.10
Classifier: License :: OSI Approved :: Apache Software License
Requires-Python: >=3.6
License-File: LICENSE
Requires-Dist: matplotlib
Provides-Extra: dev
Requires-Dist: nbdev ; extra == 'dev'
Requires-Dist: black ; extra == 'dev'
